MANIFEST.in
README.md
requirements.txt
requirements_dev.txt
setup.cfg
setup.py
bioexplorer/__init__.py
bioexplorer/bio_explorer.py
bioexplorer/metabolism.py
bioexplorer/movie_maker.py
bioexplorer/movie_scenario.py
bioexplorer/notebook_widgets.py
bioexplorer/sonata_explorer.py
bioexplorer/transfer_function.py
bioexplorer/version.py
bioexplorer.egg-info/PKG-INFO
bioexplorer.egg-info/SOURCES.txt
bioexplorer.egg-info/dependency_links.txt
bioexplorer.egg-info/requires.txt
bioexplorer.egg-info/top_level.txt
bioexplorer/core/__init__.py
bioexplorer/core/api_generator.py
bioexplorer/core/async_client.py
bioexplorer/core/base.py
bioexplorer/core/client.py
bioexplorer/core/utils.py